README.rst
setup.py
django_theming.egg-info/PKG-INFO
django_theming.egg-info/SOURCES.txt
django_theming.egg-info/dependency_links.txt
django_theming.egg-info/top_level.txt
theming/__init__.py
theming/core.py
theming/loaders.py
theming/middleware.py
theming/management/__init__.py
theming/management/commands/__init__.py
theming/management/commands/collectthemes.py
theming/templatetags/__init__.py
theming/templatetags/theming_tags.py