Metadata-Version: 1.1
Name: django-theming
Version: 1.0
Summary: Django application, implement theming concept, flexible and configurable. Allow theming for host url.
Home-page: https://github.com/achavezu89/django-theming
Author: Andres Chavez
Author-email: achavezu89@gmail.com
License: GPL
Keywords: django theme template host
Platform: UNKNOWN
Classifier: Development Status :: 4 - Beta
Classifier: Environment :: Web Environment
Classifier: Framework :: Django
Classifier: Intended Audience :: Developers
Classifier: Operating System :: OS Independent
Classifier: Programming Language :: Python
Classifier: Programming Language :: Python :: 2.7
Classifier: Topic :: Internet :: WWW/HTTP
Classifier: Topic :: Internet :: WWW/HTTP :: Dynamic Content
Classifier: Topic :: Internet :: WWW/HTTP :: WSGI
Classifier: Topic :: Software Development :: Libraries :: Application Frameworks
Classifier: Topic :: Software Development :: Libraries :: Python Modules
